easy_cloud/__init__.py
easy_cloud/easy_cloud.py
easy_cloud-0.1.4.dist-info/METADATA
easy_cloud-0.1.4.dist-info/WHEEL
easy_cloud-0.1.4.dist-info/top_level.txt
easy_cloud-0.1.4.dist-info/RECORD
