Metadata-Version: 2.1
Name: easy-cloud
Version: 0.1.4
Summary: Python package to make cloud operations easy
Home-page: https://github.com/sanchit3110/easy-cloud
Author: Sanchit Lodha
Author-email: sanchit.lodha@gmail.com
Classifier: Programming Language :: Python :: 3
Classifier: License :: OSI Approved :: MIT License
Classifier: Operating System :: OS Independent
